migrations/__init__.py
cc_django_auth-1.1.dist-info/METADATA
cc_django_auth-1.1.dist-info/WHEEL
cc_django_auth-1.1.dist-info/top_level.txt
cc_django_auth-1.1.dist-info/RECORD
